[ {
  "graph_id" : 7,
  "input_stats" : {
    "vertices" : 14,
    "edges" : 34,
    "density" : "sparse",
    "variant" : "one_cycle",
    "source" : 3,
    "weight_model" : "node"
  },
  "kosaraju_scc" : {
    "num_sccs" : 4,
    "sccs" : [ [ 0, 4, 1, 3, 9, 2, 13, 5, 6, 11, 10 ], [ 7 ], [ 12 ], [ 8 ] ],
    "operations_count" : 96,
    "execution_time_ns" : 18200
  },
  "condensation_graph" : {
    "vertices" : 4,
    "edges" : 4
  },
  "topological_sort" : {
    "topological_order" : [ 0, 10, 5, 4, 7, 13, 2, 3, 1, 9, 11, 6, 12, 8 ],
    "operations_count" : 48,
    "execution_time_ns" : 9200
  },
  "shortest_path" : {
    "source" : 3,
    "destination" : "all_reachable",
    "paths" : { },
    "operations_count" : 0,
    "execution_time_ns" : 200
  },
  "longest_path" : {
    "critical_path_length" : 0,
    "critical_path" : [ ],
    "node_durations" : [ ],
    "operations_count" : 0,
    "execution_time_ns" : 100
  },
  "total_operations_count" : 144,
  "total_execution_time_ns" : 27700
}, {
  "graph_id" : 8,
  "input_stats" : {
    "vertices" : 16,
    "edges" : 56,
    "density" : "sparse",
    "variant" : "two_cycles",
    "source" : 8,
    "weight_model" : "node"
  },
  "kosaraju_scc" : {
    "num_sccs" : 2,
    "sccs" : [ [ 0, 4, 2, 6, 3, 9, 7, 1, 13, 8, 12, 15, 5, 14, 10 ], [ 11 ] ],
    "operations_count" : 144,
    "execution_time_ns" : 26600
  },
  "condensation_graph" : {
    "vertices" : 2,
    "edges" : 1
  },
  "topological_sort" : {
    "topological_order" : [ 0, 11, 3, 6, 12, 15, 10, 2, 4, 14, 5, 7, 8, 13, 1, 9 ],
    "operations_count" : 72,
    "execution_time_ns" : 10000
  },
  "shortest_path" : {
    "source" : 8,
    "destination" : "all_reachable",
    "paths" : { },
    "operations_count" : 0,
    "execution_time_ns" : 100
  },
  "longest_path" : {
    "critical_path_length" : 0,
    "critical_path" : [ ],
    "node_durations" : [ ],
    "operations_count" : 0,
    "execution_time_ns" : 100
  },
  "total_operations_count" : 216,
  "total_execution_time_ns" : 36800
}, {
  "graph_id" : 9,
  "input_stats" : {
    "vertices" : 20,
    "edges" : 58,
    "density" : "sparse",
    "variant" : "multiple_sccs",
    "source" : 5,
    "weight_model" : "node"
  },
  "kosaraju_scc" : {
    "num_sccs" : 3,
    "sccs" : [ [ 0, 9, 8, 4, 3, 1, 7, 6, 5, 13, 10, 12, 11, 2 ], [ 15, 14 ], [ 19, 17, 16, 18 ] ],
    "operations_count" : 156,
    "execution_time_ns" : 30600
  },
  "condensation_graph" : {
    "vertices" : 3,
    "edges" : 2
  },
  "topological_sort" : {
    "topological_order" : [ 0, 1, 2, 3, 4, 5, 6, 7, 8, 9, 10, 15, 14, 19, 16, 17, 18, 11, 12, 13 ],
    "operations_count" : 78,
    "execution_time_ns" : 17000
  },
  "shortest_path" : {
    "source" : 5,
    "destination" : "all_reachable",
    "paths" : { },
    "operations_count" : 0,
    "execution_time_ns" : 200
  },
  "longest_path" : {
    "critical_path_length" : 0,
    "critical_path" : [ ],
    "node_durations" : [ ],
    "operations_count" : 0,
    "execution_time_ns" : 200
  },
  "total_operations_count" : 234,
  "total_execution_time_ns" : 48000
} ]